simple_vite/__init__.py
simple_vite/templatetags/__init__.py
simple_vite/templatetags/vite.py
django_simple_vite-1.0.0.dist-info/LICENSE.txt
django_simple_vite-1.0.0.dist-info/METADATA
django_simple_vite-1.0.0.dist-info/WHEEL
django_simple_vite-1.0.0.dist-info/top_level.txt
django_simple_vite-1.0.0.dist-info/RECORD
