Metadata-Version: 2.1
Name: django-simple-vite
Version: 1.0.0
Summary: A simple Django app to integrate Vite.js easily in your Django project.
Home-page: https://github.com/baxeico/django-simple-vite
Author: Augusto Destrero
Author-email: augusto@guguweb.com
License: MIT
Keywords: django,vitejs
Platform: UNKNOWN
Requires-Dist: Django (>=3.2)
